cornsnake/__init__.py
cornsnake/config.py
cornsnake/decorators.py
cornsnake/setup.py
cornsnake/util_base64.py
cornsnake/util_color.py
cornsnake/util_date.py
cornsnake/util_dependencies.py
cornsnake/util_dict.py
cornsnake/util_dir.py
cornsnake/util_file.py
cornsnake/util_git.py
cornsnake/util_input.py
cornsnake/util_json.py
cornsnake/util_list.py
cornsnake/util_log.py
cornsnake/util_markdown_table.py
cornsnake/util_network.py
cornsnake/util_object.py
cornsnake/util_os.py
cornsnake/util_pdf.py
cornsnake/util_pick.py
cornsnake/util_print.py
cornsnake/util_proc.py
cornsnake/util_progress.py
cornsnake/util_robust_delete.py
cornsnake/util_string.py
cornsnake/util_text.py
cornsnake/util_time.py
cornsnake/util_toml.py
cornsnake/util_validate.py
cornsnake/util_wait.py
cornsnake/util_yaml.py
cornsnake/util_zip.py
cornsnake/zip_dir.py
cornsnake-0.1.1.dist-info/licenses/LICENSE
cornsnake-0.1.1.dist-info/METADATA
cornsnake-0.1.1.dist-info/WHEEL
cornsnake-0.1.1.dist-info/top_level.txt
cornsnake-0.1.1.dist-info/RECORD
