Metadata-Version: 2.4
Name: cornsnake
Version: 0.1.1
Summary: Wrap common Python utilities for working with files, git, ZIP, lists, processes, dates and times.
Home-page: https://github.com/mrseanryan/cornsnake
Author: Sean Ryan
Author-email: Sean Ryan <mr.sean.ryan@gmail.com>
License-Expression: MIT
Project-URL: Homepage, https://github.com/mrseanryan/cornsnake
Project-URL: Documentation, http://docs.mrseanryan.cornsnake.s3-website-eu-west-1.amazonaws.com/
Project-URL: Issues, https://github.com/mrseanryan/cornsnake/issues
Project-URL: Source, https://github.com/mrseanryan/cornsnake
Keywords: python,files,lists,utils,dates,processes
Classifier: Programming Language :: Python
Classifier: Programming Language :: Python :: 3
Classifier: Development Status :: 5 - Production/Stable
Classifier: Environment :: Console
Classifier: Intended Audience :: Developers
Classifier: Operating System :: OS Independent
Classifier: Topic :: Software Development :: Libraries :: Python Modules
Requires-Python: >=3.11
License-File: LICENSE
Provides-Extra: dev
Requires-Dist: bumpver~=2023.1129; extra == "dev"
Requires-Dist: parameterized~=0.9.0; extra == "dev"
Requires-Dist: PyMuPDF~=1.26.5; extra == "dev"
Requires-Dist: build~=1.0.3; extra == "dev"
Requires-Dist: bumpver~=2023.1129; extra == "dev"
Requires-Dist: parameterized~=0.9.0; extra == "dev"
Requires-Dist: pdoc~=14.4.0; extra == "dev"
Requires-Dist: pip-tools~=7.3.0; extra == "dev"
Requires-Dist: twine~=5.0.0; extra == "dev"
Requires-Dist: ruff~=0.3.4; extra == "dev"
Requires-Dist: mypy~=1.14.0; extra == "dev"
Requires-Dist: pkginfo~=1.12.1.2; extra == "dev"
Dynamic: license-file
